tru_music/__init__.py
tru_music/artist_album.py
tru_music/scripts/__init__.py
tru_music/scripts/cleanup.py
tru_music/scripts/trumusic.py
trumusic-1.3.6.dist-info/METADATA
trumusic-1.3.6.dist-info/WHEEL
trumusic-1.3.6.dist-info/entry_points.txt
trumusic-1.3.6.dist-info/top_level.txt
trumusic-1.3.6.dist-info/RECORD
