Metadata-Version: 2.4
Name: TruMusic
Version: 1.3.6
Summary: Audio file auto-tagger
Author-email: Jacob Truman <jacob.truman@gmail.com>
Project-URL: homepage, https://github.com/jacobtruman/TruMusic
Project-URL: documentation, https://github.com/jacobtruman/TruMusic
Project-URL: repository, https://github.com/jacobtruman/TruMusic
Requires-Python: <4,>=3.7
Requires-Dist: mutagen
Requires-Dist: requests
Requires-Dist: ytmusicapi==1.9.1
Requires-Dist: yt-dlp
Requires-Dist: TruLogger
Requires-Dist: ascii_magic
